{
    "status": "BEST_REF",
    "results": [
        {
            "name": "Crassula perforata Thunb.",
            "id": "1423481",
            "score": 0.57557
        },
        {
            "name": "Crassula pellucida L.",
            "id": "1528554",
            "score": 0.09441
        },
        {
            "name": "Honckenya peploides (L.) Ehrh.",
            "id": "1397403",
            "score": 0.07038
        },
        {
            "name": "Crassula rupestris L.f.",
            "id": "1528572",
            "score": 0.06237
        },
        {
            "name": "Crassula lactea Aiton",
            "id": "1528514",
            "score": 0.00578
        },
        {
            "name": "Crassula capitella Thunb.",
            "id": "1528452",
            "score": 0.00525
        },
        {
            "name": "Callisia repens (Jacq.) L.",
            "id": "1409254",
            "score": 0.00432
        },
        {
            "name": "Anacampseros arachnoides (Haw.) Sims",
            "id": "1454012",
            "score": 0.00254
        },
        {
            "name": "Sedum hemsleyanum Rose",
            "id": "1713719",
            "score": 0.0022
        },
        {
            "name": "Sedum mendozae (Glass & Cházaro) V.V.Byalt",
            "id": "1822648",
            "score": 0.00219
        },
        {
            "name": "Crassula multicava Lem.",
            "id": "1363618",
            "score": 0.00192
        },
        {
            "name": "Crassula orbicularis L.",
            "id": "1365917",
            "score": 0.00168
        },
        {
            "name": "Mesembryanthemum cordifolium L.f.",
            "id": "1418211",
            "score": 0.0016
        },
        {
            "name": "Orostachys malacophylla (Pall.) Fisch.",
            "id": "1418538",
            "score": 0.00144
        },
        {
            "name": "Crassula volkensii Engl.",
            "id": "1528613",
            "score": 0.00128
        },
        {
            "name": "Graptopetalum macdougallii Alexander",
            "id": "1528813",
            "score": 0.00124
        },
        {
            "name": "Sedum spathulifolium Hook.",
            "id": "1413755",
            "score": 0.00123
        },
        {
            "name": "Crassula tetragona L.",
            "id": "1363620",
            "score": 0.00118
        },
        {
            "name": "Callisia navicularis (Ortgies) D.R.Hunt",
            "id": "1418467",
            "score": 0.00116
        },
        {
            "name": "Sedum burrito Moran",
            "id": "1529107",
            "score": 0.00114
        }
    ]
}