{
    "status": "OK",
    "results": [
        {
            "name": "Prunella vulgaris L.",
            "id": "1356109",
            "score": 0.19377
        },
        {
            "name": "Melampyrum arvense L.",
            "id": "1393779",
            "score": 0.03885
        },
        {
            "name": "Prunella laciniata (L.) L.",
            "id": "1358854",
            "score": 0.02297
        },
        {
            "name": "Centaurea nigra L.",
            "id": "1357438",
            "score": 0.00616
        },
        {
            "name": "Betonica officinalis L.",
            "id": "1400126",
            "score": 0.00401
        },
        {
            "name": "Prunella grandiflora (L.) Turra",
            "id": "1737424",
            "score": 0.00366
        },
        {
            "name": "Scutellaria alpina L.",
            "id": "1397490",
            "score": 0.00321
        },
        {
            "name": "Coris monspeliensis L.",
            "id": "1356305",
            "score": 0.00307
        },
        {
            "name": "Lavandula stoechas L.",
            "id": "1358766",
            "score": 0.00302
        },
        {
            "name": "Pedicularis verticillata L.",
            "id": "1394451",
            "score": 0.00267
        },
        {
            "name": "Rhinanthus minor L.",
            "id": "1395169",
            "score": 0.00243
        },
        {
            "name": "Rhinanthus alectorolophus (Scop.) Pollich",
            "id": "1395162",
            "score": 0.00231
        },
        {
            "name": "Centaurea pectinata L.",
            "id": "1391028",
            "score": 0.00211
        },
        {
            "name": "Trifolium angustifolium L.",
            "id": "1359483",
            "score": 0.00191
        },
        {
            "name": "Phleum arenarium L.",
            "id": "1361361",
            "score": 0.0019
        },
        {
            "name": "Stachys palustris L.",
            "id": "1397503",
            "score": 0.00189
        },
        {
            "name": "Sideritis ovata Cav.",
            "id": "1563781",
            "score": 0.00168
        },
        {
            "name": "Bellardia trixago (L.) All.",
            "id": "1426015",
            "score": 0.00168
        },
        {
            "name": "Centaurea jacea L.",
            "id": "1362427",
            "score": 0.00168
        },
        {
            "name": "Potentilla grandiflora L.",
            "id": "1394848",
            "score": 0.00142
        },
        {
            "name": "Sideritis hyssopifolia L.",
            "id": "1362495",
            "score": 0.00141
        },
        {
            "name": "Veronica spicata L.",
            "id": "1397522",
            "score": 0.00141
        },
        {
            "name": "Centaurea phrygia L.",
            "id": "1390981",
            "score": 0.00132
        },
        {
            "name": "Sesleria albicans Kit. ex Schult.",
            "id": "1722440",
            "score": 0.00123
        },
        {
            "name": "Salvia nemorosa L.",
            "id": "1397479",
            "score": 0.00116
        },
        {
            "name": "Verbena rigida Spreng.",
            "id": "1356211",
            "score": 0.00107
        },
        {
            "name": "Lythrum salicaria L.",
            "id": "1356023",
            "score": 0.00107
        },
        {
            "name": "Orobanche rapum-genistae Thuill.",
            "id": "1359734",
            "score": 0.00106
        },
        {
            "name": "Anacamptis pyramidalis (L.) Rich.",
            "id": "1361634",
            "score": 0.00104
        }
    ]
}