{
    "status": "BEST_REF",
    "results": [
        {
            "name": "Tragopogon pratensis L.",
            "id": "1396832",
            "score": 0.7726
        },
        {
            "name": "Pseudopodospermum hispanicum (L.) Zaika, Sukhor. & N.Kilian",
            "id": "1739189",
            "score": 0.06103
        },
        {
            "name": "Scorzonera humilis L.",
            "id": "1396115",
            "score": 0.04859
        },
        {
            "name": "Tragopogon orientalis L.",
            "id": "1524939",
            "score": 0.01178
        },
        {
            "name": "Tragopogon dubius Scop.",
            "id": "1364167",
            "score": 0.00785
        },
        {
            "name": "Scorzonera laciniata L.",
            "id": "1437978",
            "score": 0.00565
        },
        {
            "name": "Arnica montana L.",
            "id": "1396472",
            "score": 0.00259
        },
        {
            "name": "Gelasia hirsuta (Gouan) Zaika, Sukhor. & N.Kilian",
            "id": "1743889",
            "score": 0.00173
        }
    ]
}