{
    "status": "BEST_REF",
    "results": [
        {
            "name": "Agrimonia eupatoria L.",
            "id": "1363994",
            "score": 0.64513
        },
        {
            "name": "Agrimonia procera Wallr.",
            "id": "1389589",
            "score": 0.30336
        },
        {
            "name": "Verbascum nigrum L.",
            "id": "1397520",
            "score": 0.00449
        },
        {
            "name": "Verbascum lychnitis L.",
            "id": "1360531",
            "score": 0.00159
        },
        {
            "name": "Agrimonia gryposepala Wallr.",
            "id": "1411302",
            "score": 0.00157
        },
        {
            "name": "Agrimonia pilosa Ledeb.",
            "id": "1666260",
            "score": 0.00121
        },
        {
            "name": "Agrimonia striata Michx.",
            "id": "1411350",
            "score": 0.00117
        }
    ]
}