{
    "status": "BEST_REF",
    "results": [
        {
            "name": "Lilium bulbiferum L.",
            "id": "1393532",
            "score": 0.83275
        },
        {
            "name": "Lilium longiflorum Thunb.",
            "id": "1408290",
            "score": 0.01436
        },
        {
            "name": "Lilium candidum L.",
            "id": "1361623",
            "score": 0.00778
        },
        {
            "name": "Lilium regale E.H.Wilson",
            "id": "1419333",
            "score": 0.00378
        },
        {
            "name": "Hemerocallis fulva (L.) L.",
            "id": "1392748",
            "score": 0.00343
        },
        {
            "name": "Lilium martagon L.",
            "id": "1393534",
            "score": 0.00297
        },
        {
            "name": "Lilium lancifolium Thunb.",
            "id": "1393528",
            "score": 0.00292
        },
        {
            "name": "Lilium rhodopeum Delip.",
            "id": "1588942",
            "score": 0.00256
        },
        {
            "name": "Iphigenia indica (L.) A.Gray ex Kunth",
            "id": "1496804",
            "score": 0.00146
        },
        {
            "name": "Crinum bulbispermum (Burm.f.) Milne-Redh. & Schweick.",
            "id": "1397678",
            "score": 0.00138
        },
        {
            "name": "Hippeastrum correiense (Bury) Worsley",
            "id": "1453298",
            "score": 0.00135
        },
        {
            "name": "Lilium tsingtauense Gilg",
            "id": "1588957",
            "score": 0.00101
        }
    ]
}