{
    "status": "BEST_REF",
    "results": [
        {
            "name": "Eragrostis minor Host",
            "id": "1363555",
            "score": 0.93186
        },
        {
            "name": "Eragrostis cilianensis (All.) Vignolo ex Janch.",
            "id": "1363551",
            "score": 0.02071
        },
        {
            "name": "Eragrostis barrelieri Daveau",
            "id": "1363550",
            "score": 0.01568
        },
        {
            "name": "Eragrostis racemosa (Thunb.) Steud.",
            "id": "1365434",
            "score": 0.00538
        },
        {
            "name": "Eragrostis multicaulis Steud.",
            "id": "1361256",
            "score": 0.00459
        },
        {
            "name": "Eragrostis pilosa (L.) P.Beauv.",
            "id": "1392016",
            "score": 0.00351
        },
        {
            "name": "Agrostis capillaris L.",
            "id": "1361133",
            "score": 0.00163
        },
        {
            "name": "Polypogon viridis (Gouan) Breistr.",
            "id": "1363403",
            "score": 0.00133
        },
        {
            "name": "Digitaria sanguinalis (L.) Scop.",
            "id": "1363424",
            "score": 0.00128
        },
        {
            "name": "Eragrostis tenella (L.) P.Beauv. ex Roem. & Schult.",
            "id": "1397791",
            "score": 0.00099
        },
        {
            "name": "Setaria verticillata (L.) P.Beauv.",
            "id": "1396252",
            "score": 0.00044
        },
        {
            "name": "Sporobolus coromandelianus (Retz.) Kunth",
            "id": "1364526",
            "score": 0.00042
        },
        {
            "name": "Cynodon dactylon (L.) Pers.",
            "id": "1363526",
            "score": 0.00041
        }
    ]
}