{
    "status": "BEST_REF",
    "results": [
        {
            "name": "Ligustrum japonicum Thunb.",
            "id": "1397735",
            "score": 0.62455
        },
        {
            "name": "Ligustrum lucidum W.T.Aiton",
            "id": "1393525",
            "score": 0.24619
        },
        {
            "name": "Lagerstroemia indica L.",
            "id": "1376509",
            "score": 0.07941
        },
        {
            "name": "Grevillea robusta A.Cunn. ex R.Br.",
            "id": "1394929",
            "score": 0.06089
        },
        {
            "name": "Fraxinus excelsior L.",
            "id": "1361864",
            "score": 0.03421
        },
        {
            "name": "Betula utilis D.Don",
            "id": "1400127",
            "score": 0.02084
        },
        {
            "name": "Fraxinus angustifolia Vahl",
            "id": "1362009",
            "score": 0.02019
        },
        {
            "name": "Prunus lusitanica L.",
            "id": "1360322",
            "score": 0.01133
        },
        {
            "name": "Celtis australis L.",
            "id": "1361742",
            "score": 0.00899
        },
        {
            "name": "Eugenia uniflora L.",
            "id": "1382851",
            "score": 0.00661
        },
        {
            "name": "Ilex rotunda Thunb.",
            "id": "1420717",
            "score": 0.0061
        },
        {
            "name": "Scandosorbus intermedia (Ehrh.) Sennikov",
            "id": "1737669",
            "score": 0.00608
        },
        {
            "name": "Acer negundo L.",
            "id": "1356458",
            "score": 0.0057
        },
        {
            "name": "Sorbus aucuparia L.",
            "id": "1362987",
            "score": 0.00566
        },
        {
            "name": "Annona muricata L.",
            "id": "1386673",
            "score": 0.00481
        },
        {
            "name": "Ficus religiosa L.",
            "id": "1405284",
            "score": 0.00475
        },
        {
            "name": "Simarouba amara Aubl.",
            "id": "1403544",
            "score": 0.00473
        },
        {
            "name": "Osmanthus fragrans Lour.",
            "id": "1394028",
            "score": 0.00433
        },
        {
            "name": "Viburnum tinus L.",
            "id": "1356793",
            "score": 0.004
        },
        {
            "name": "Cinnamomum camphora (L.) J.Presl",
            "id": "1389656",
            "score": 0.00386
        },
        {
            "name": "Prunus serrulata Lindl.",
            "id": "1394953",
            "score": 0.00366
        },
        {
            "name": "Cornus mas L.",
            "id": "1391354",
            "score": 0.00359
        },
        {
            "name": "Aria edulis (Willd.) M.Roem.",
            "id": "1737559",
            "score": 0.00326
        },
        {
            "name": "Acer buergerianum Miq.",
            "id": "1390598",
            "score": 0.00285
        },
        {
            "name": "Styphnolobium japonicum (L.) Schott",
            "id": "1369068",
            "score": 0.0027
        },
        {
            "name": "Toona ciliata M.Roem.",
            "id": "1419485",
            "score": 0.00249
        },
        {
            "name": "Prunus padus L.",
            "id": "1360324",
            "score": 0.00247
        },
        {
            "name": "Ligustrum ovalifolium Hassk.",
            "id": "1393526",
            "score": 0.00237
        },
        {
            "name": "Amelanchier canadensis (L.) Medik.",
            "id": "1397734",
            "score": 0.00227
        },
        {
            "name": "Laburnum anagyroides Medik.",
            "id": "1397419",
            "score": 0.00227
        },
        {
            "name": "Ligustrum sinense Lour.",
            "id": "1390584",
            "score": 0.00208
        },
        {
            "name": "Quercus ilex L.",
            "id": "1357416",
            "score": 0.00207
        },
        {
            "name": "Castanea sativa Mill.",
            "id": "1358610",
            "score": 0.00197
        },
        {
            "name": "Cornus sanguinea L.",
            "id": "1397356",
            "score": 0.00191
        },
        {
            "name": "Morus alba L.",
            "id": "1359658",
            "score": 0.00171
        },
        {
            "name": "Ficus sycomorus L.",
            "id": "1361856",
            "score": 0.00167
        },
        {
            "name": "Rhodosphaera rhodanthema (F.Muell.) Engl.",
            "id": "1805134",
            "score": 0.00161
        },
        {
            "name": "Elaeagnus multiflora Thunb.",
            "id": "1397955",
            "score": 0.00159
        },
        {
            "name": "Lagerstroemia speciosa (L.) Pers.",
            "id": "1376510",
            "score": 0.00146
        },
        {
            "name": "Diospyros virginiana L.",
            "id": "1389362",
            "score": 0.00145
        },
        {
            "name": "Acer saccharinum L.",
            "id": "1391667",
            "score": 0.00139
        },
        {
            "name": "Annona montana Macfad.",
            "id": "1401227",
            "score": 0.00137
        },
        {
            "name": "Ficus benjamina L.",
            "id": "1382112",
            "score": 0.00132
        },
        {
            "name": "Ostrya carpinifolia Scop.",
            "id": "1394357",
            "score": 0.00127
        },
        {
            "name": "Ligustrum vulgare L.",
            "id": "1359675",
            "score": 0.00125
        },
        {
            "name": "Albizia lebbeck (L.) Benth.",
            "id": "1366605",
            "score": 0.00123
        },
        {
            "name": "Camellia japonica L.",
            "id": "1379149",
            "score": 0.0012
        },
        {
            "name": "Eperua grandiflora (Aubl.) Baill.",
            "id": "1400562",
            "score": 0.00119
        },
        {
            "name": "Phytolacca dioica L.",
            "id": "1356063",
            "score": 0.00116
        },
        {
            "name": "Melia azedarach L.",
            "id": "1363624",
            "score": 0.0011
        },
        {
            "name": "Quercus glauca Thunb.",
            "id": "1548261",
            "score": 0.00108
        },
        {
            "name": "Senna siamea (Lam.) H.S.Irwin & Barneby",
            "id": "1408690",
            "score": 0.00108
        },
        {
            "name": "Carpinus betulus L.",
            "id": "1390952",
            "score": 0.00107
        },
        {
            "name": "Morus nigra L.",
            "id": "1359659",
            "score": 0.00107
        },
        {
            "name": "Quercus suber L.",
            "id": "1358617",
            "score": 0.00106
        },
        {
            "name": "Fraxinus ornus L.",
            "id": "1362963",
            "score": 0.00106
        },
        {
            "name": "Salix caprea L.",
            "id": "1395765",
            "score": 0.00104
        },
        {
            "name": "Broussonetia papyrifera (L.) L'Hér. ex Vent.",
            "id": "1362912",
            "score": 0.00102
        },
        {
            "name": "Alnus glutinosa (L.) Gaertn.",
            "id": "1356608",
            "score": 0.00102
        },
        {
            "name": "Quercus × turneri Willd.",
            "id": "1744146",
            "score": 0.001
        },
        {
            "name": "Schinus terebinthifolia Raddi",
            "id": "1396078",
            "score": 0.00093
        },
        {
            "name": "Crataegus × lavallei Herincq ex Lavallée",
            "id": "1843990",
            "score": 0.00091
        },
        {
            "name": "Acer griseum (Franch.) Pax",
            "id": "1390600",
            "score": 0.00089
        },
        {
            "name": "Amelanchier × lamarckii F.G.Schroed.",
            "id": "1737557",
            "score": 0.00089
        },
        {
            "name": "Simarouba glauca DC.",
            "id": "1438311",
            "score": 0.00088
        },
        {
            "name": "Acer pseudoplatanus L.",
            "id": "1356460",
            "score": 0.00087
        },
        {
            "name": "Acer tataricum L.",
            "id": "1398270",
            "score": 0.00077
        },
        {
            "name": "Syringa vulgaris L.",
            "id": "1396503",
            "score": 0.00077
        },
        {
            "name": "Alnus incana (L.) Moench",
            "id": "1397308",
            "score": 0.00075
        },
        {
            "name": "Brachychiton acerifolius (A.Cunn. ex G.Don) F.Muell.",
            "id": "1419406",
            "score": 0.00075
        },
        {
            "name": "Plinia cauliflora (Mart.) Kausel",
            "id": "1419577",
            "score": 0.00074
        },
        {
            "name": "Acer macrophyllum Pursh",
            "id": "1412158",
            "score": 0.00073
        },
        {
            "name": "Tsuga heterophylla (Raf.) Sarg.",
            "id": "1396904",
            "score": 0.00071
        },
        {
            "name": "Fraxinus americana L.",
            "id": "1397619",
            "score": 0.00069
        },
        {
            "name": "Croton urucurana Baill.",
            "id": "1418816",
            "score": 0.00068
        },
        {
            "name": "Acer davidii Franch.",
            "id": "1390684",
            "score": 0.00067
        },
        {
            "name": "Platanus orientalis L.",
            "id": "1362358",
            "score": 0.00066
        },
        {
            "name": "Fraxinus latifolia Benth.",
            "id": "1412090",
            "score": 0.00066
        },
        {
            "name": "Laburnum alpinum (Mill.) Bercht. & J.Presl",
            "id": "1393412",
            "score": 0.00066
        },
        {
            "name": "Eugenia uruguayensis Cambess.",
            "id": "1605091",
            "score": 0.00065
        },
        {
            "name": "Fraxinus pennsylvanica Marshall",
            "id": "1392363",
            "score": 0.00062
        },
        {
            "name": "Quercus conferta Kit.",
            "id": "1742823",
            "score": 0.00062
        },
        {
            "name": "Hedlundia hybrida (L.) Sennikov & Kurtto",
            "id": "1737586",
            "score": 0.00061
        },
        {
            "name": "Salix atrocinerea Brot.",
            "id": "1360451",
            "score": 0.0006
        },
        {
            "name": "Eperua falcata Aubl.",
            "id": "1400561",
            "score": 0.00059
        },
        {
            "name": "Deutzia scabra Thunb.",
            "id": "1391675",
            "score": 0.00057
        },
        {
            "name": "Toona sinensis (A.Juss.) M.Roem.",
            "id": "1752847",
            "score": 0.00054
        },
        {
            "name": "Quercus rubra L.",
            "id": "1395035",
            "score": 0.00054
        },
        {
            "name": "Calliandra surinamensis Benth.",
            "id": "1366525",
            "score": 0.00053
        },
        {
            "name": "Quercus cerris L.",
            "id": "1395020",
            "score": 0.00052
        },
        {
            "name": "Arbutus andrachne L.",
            "id": "1395933",
            "score": 0.00052
        },
        {
            "name": "Gleditsia triacanthos L.",
            "id": "1363687",
            "score": 0.0005
        },
        {
            "name": "× Chitalpa tashkentensis T.S.Elias & Wisura",
            "id": "1845005",
            "score": 0.0005
        }
    ]
}