{
    "status": "BEST_REF",
    "results": [
        {
            "name": "Pyracantha coccinea M.Roem.",
            "id": "1394994",
            "score": 0.78137
        },
        {
            "name": "Pyracantha crenulata (D.Don) M.Roem.",
            "id": "1729475",
            "score": 0.04907
        },
        {
            "name": "Spiraea nipponica Maxim.",
            "id": "1398563",
            "score": 0.01891
        },
        {
            "name": "Aronia melanocarpa (Michx.) Elliott",
            "id": "1398450",
            "score": 0.00737
        },
        {
            "name": "Prunus mahaleb L.",
            "id": "1360323",
            "score": 0.00364
        },
        {
            "name": "Pyracantha koidzumii (Hayata) Rehder",
            "id": "1389031",
            "score": 0.0034
        },
        {
            "name": "Spiraea × vanhouttei (Briot) Carrière",
            "id": "1844864",
            "score": 0.00264
        },
        {
            "name": "Photinia serratifolia (Desf.) Kalkman",
            "id": "1420392",
            "score": 0.00181
        },
        {
            "name": "Hedlundia thuringiaca (Nyman) Sennikov & Kurtto",
            "id": "1738935",
            "score": 0.0016
        },
        {
            "name": "Pourthiaea villosa (Thunb.) Decne.",
            "id": "1720055",
            "score": 0.00147
        },
        {
            "name": "Scandosorbus intermedia (Ehrh.) Sennikov",
            "id": "1737669",
            "score": 0.0014
        },
        {
            "name": "Crataegus monogyna Jacq.",
            "id": "1363988",
            "score": 0.00126
        },
        {
            "name": "Cotoneaster coriaceus Franch.",
            "id": "1390095",
            "score": 0.00112
        },
        {
            "name": "Sorbus aucuparia L.",
            "id": "1362987",
            "score": 0.00102
        }
    ]
}