{
    "status": "BEST_REF",
    "results": [
        {
            "name": "Lagerstroemia indica L.",
            "id": "1376509",
            "score": 0.64057
        },
        {
            "name": "Lagerstroemia speciosa (L.) Pers.",
            "id": "1376510",
            "score": 0.22265
        },
        {
            "name": "Vitex trifolia L.",
            "id": "1408829",
            "score": 0.00176
        },
        {
            "name": "Lagerstroemia limii Merr.",
            "id": "1590983",
            "score": 0.00111
        }
    ]
}