{
    "status": "BEST_REF",
    "results": [
        {
            "name": "Epipactis helleborine (L.) Crantz",
            "id": "1362294",
            "score": 0.72785
        },
        {
            "name": "Epipactis muelleri Godfery",
            "id": "1391962",
            "score": 0.0668
        },
        {
            "name": "Epipactis atrorubens (Hoffm.) Besser",
            "id": "1391953",
            "score": 0.04762
        },
        {
            "name": "Cephalanthera damasonium (Mill.) Druce",
            "id": "1361635",
            "score": 0.01358
        },
        {
            "name": "Epipactis bugacensis Robatsch",
            "id": "1398205",
            "score": 0.00948
        },
        {
            "name": "Epipactis purpurata Sm.",
            "id": "1391967",
            "score": 0.00672
        },
        {
            "name": "Veratrum album L.",
            "id": "1396991",
            "score": 0.00621
        },
        {
            "name": "Cypripedium calceolus L.",
            "id": "1391518",
            "score": 0.00386
        },
        {
            "name": "Epipactis leptochila (Godfery) Godfery",
            "id": "1391960",
            "score": 0.00378
        },
        {
            "name": "Cephalanthera longifolia (L.) Fritsch",
            "id": "1361636",
            "score": 0.00367
        },
        {
            "name": "Lilium martagon L.",
            "id": "1393534",
            "score": 0.00344
        },
        {
            "name": "Epipactis phyllanthes G.E.Sm.",
            "id": "1391964",
            "score": 0.00268
        },
        {
            "name": "Ophrys sphegodes Mill.",
            "id": "1361669",
            "score": 0.00218
        },
        {
            "name": "Epipactis dunensis (T.Stephenson & T.A.Stephenson) Godfery",
            "id": "1621501",
            "score": 0.00188
        },
        {
            "name": "Dactylorhiza viridis (L.) R.M.Bateman, Pridgeon & M.W.Chase",
            "id": "1391619",
            "score": 0.00165
        },
        {
            "name": "Ophrys apifera Huds.",
            "id": "1361656",
            "score": 0.00163
        },
        {
            "name": "Epipactis papillosa Franch. & Sav.",
            "id": "1621523",
            "score": 0.0016
        },
        {
            "name": "Epipactis persica (Soó) Hausskn. ex Nannf.",
            "id": "1621524",
            "score": 0.00142
        },
        {
            "name": "Epipactis palustris (L.) Crantz",
            "id": "1391963",
            "score": 0.00123
        },
        {
            "name": "Steveniella satyrioides (Spreng.) Schltr.",
            "id": "1634424",
            "score": 0.00104
        },
        {
            "name": "Epipactis microphylla (Ehrh.) Sw.",
            "id": "1391961",
            "score": 0.00039
        },
        {
            "name": "Veratrum viride Aiton",
            "id": "1414166",
            "score": 0.00038
        }
    ]
}