{
    "status": "BEST_REF",
    "results": [
        {
            "name": "Prunus cerasifera Ehrh.",
            "id": "1360317",
            "score": 0.48165
        },
        {
            "name": "Malus hupehensis (Pamp.) Rehder",
            "id": "1393732",
            "score": 0.09991
        },
        {
            "name": "Prunus brigantina Vill.",
            "id": "1394945",
            "score": 0.07017
        },
        {
            "name": "Malus baccata (L.) Borkh.",
            "id": "1393736",
            "score": 0.03274
        },
        {
            "name": "Prunus × fruticans Weihe",
            "id": "1667948",
            "score": 0.02144
        },
        {
            "name": "Malus × floribunda Siebold ex Van Houtte",
            "id": "1782760",
            "score": 0.01804
        },
        {
            "name": "Prunus japonica Thunb.",
            "id": "1394940",
            "score": 0.01738
        },
        {
            "name": "Prunus domestica L.",
            "id": "1360319",
            "score": 0.01382
        },
        {
            "name": "Malus sylvestris (L.) Mill.",
            "id": "1420379",
            "score": 0.00771
        },
        {
            "name": "Malus prunifolia (Willd.) Borkh.",
            "id": "1412671",
            "score": 0.0054
        },
        {
            "name": "Rhamnus saxatilis Jacq.",
            "id": "1395158",
            "score": 0.00357
        },
        {
            "name": "Prunus umbellata Elliott",
            "id": "1436948",
            "score": 0.00318
        },
        {
            "name": "Prunus spinosa L.",
            "id": "1360326",
            "score": 0.00295
        },
        {
            "name": "Flacourtia jangomas (Lour.) Raeusch.",
            "id": "1382989",
            "score": 0.00198
        },
        {
            "name": "Prunus salicina Lindl.",
            "id": "1420425",
            "score": 0.00184
        },
        {
            "name": "Prunus cerasus L.",
            "id": "1360318",
            "score": 0.00168
        },
        {
            "name": "Prunus × cistena N.E.Hansen ex Koehne",
            "id": "1667925",
            "score": 0.00145
        },
        {
            "name": "Malus × purpurea (A.Barbier) Rehder",
            "id": "1844417",
            "score": 0.00143
        },
        {
            "name": "Crataegus persimilis Sarg.",
            "id": "1391430",
            "score": 0.00143
        },
        {
            "name": "Chaenomeles speciosa (Sweet) Nakai",
            "id": "1391104",
            "score": 0.0014
        },
        {
            "name": "Viburnum prunifolium L.",
            "id": "1417592",
            "score": 0.00119
        },
        {
            "name": "Euonymus latifolius (L.) Mill.",
            "id": "1392238",
            "score": 0.00112
        },
        {
            "name": "Crataegus crus-galli L.",
            "id": "1391433",
            "score": 0.00107
        }
    ]
}