{
    "status": "OK",
    "results": [
        {
            "name": "Rumex acetosella L.",
            "id": "1356082",
            "score": 0.08896
        },
        {
            "name": "Rumex sanguineus L.",
            "id": "1395686",
            "score": 0.04852
        },
        {
            "name": "Rumex acetosa L.",
            "id": "1360120",
            "score": 0.04411
        },
        {
            "name": "Fallopia convolvulus (L.) Á.Löve",
            "id": "1392250",
            "score": 0.03335
        },
        {
            "name": "Fagopyrum esculentum Moench",
            "id": "1356095",
            "score": 0.0318
        },
        {
            "name": "Dichondra micrantha Urb.",
            "id": "1364071",
            "score": 0.02201
        },
        {
            "name": "Lipandra polysperma (L.) S.Fuentes, Uotila & Borsch",
            "id": "1389976",
            "score": 0.02136
        },
        {
            "name": "Lysimachia nemorum L.",
            "id": "1397432",
            "score": 0.01986
        },
        {
            "name": "Lonicera caprifolium L.",
            "id": "1393632",
            "score": 0.01887
        },
        {
            "name": "Atriplex hortensis L.",
            "id": "1363180",
            "score": 0.01514
        },
        {
            "name": "Mirabilis jalapa L.",
            "id": "1362100",
            "score": 0.01415
        },
        {
            "name": "Prunus armeniaca L.",
            "id": "1362982",
            "score": 0.01268
        },
        {
            "name": "Theligonum cynocrambe L.",
            "id": "1360435",
            "score": 0.01256
        },
        {
            "name": "Stellaria media (L.) Vill.",
            "id": "1356571",
            "score": 0.00906
        },
        {
            "name": "Samolus valerandi L.",
            "id": "1361883",
            "score": 0.0088
        },
        {
            "name": "Fallopia dumetorum (L.) Holub",
            "id": "1392251",
            "score": 0.00878
        },
        {
            "name": "Amaranthus tricolor L.",
            "id": "1363257",
            "score": 0.0082
        },
        {
            "name": "Ceratostigma plumbaginoides Bunge",
            "id": "1391099",
            "score": 0.00536
        },
        {
            "name": "Rumex pulcher L.",
            "id": "1356314",
            "score": 0.00508
        },
        {
            "name": "Beta vulgaris L.",
            "id": "1363199",
            "score": 0.00467
        },
        {
            "name": "Amaranthus deflexus L.",
            "id": "1363250",
            "score": 0.00435
        },
        {
            "name": "Thymus pulegioides L.",
            "id": "1396792",
            "score": 0.004
        },
        {
            "name": "Pyrola rotundifolia L.",
            "id": "1395001",
            "score": 0.00374
        },
        {
            "name": "Lonicera etrusca Santi",
            "id": "1356784",
            "score": 0.00369
        },
        {
            "name": "Veronica serpyllifolia L.",
            "id": "1364066",
            "score": 0.0036
        },
        {
            "name": "Eruca vesicaria (L.) Cav.",
            "id": "1356328",
            "score": 0.00341
        },
        {
            "name": "Amaranthus blitum L.",
            "id": "1356472",
            "score": 0.00338
        },
        {
            "name": "Persicaria capitata (Buch.-Ham. ex D.Don) H.Gross",
            "id": "1394749",
            "score": 0.00301
        },
        {
            "name": "Amaranthus cruentus L.",
            "id": "1363249",
            "score": 0.003
        },
        {
            "name": "Crepis sancta (L.) Bornm.",
            "id": "1357546",
            "score": 0.00275
        },
        {
            "name": "Rumex bucephalophorus L.",
            "id": "1360127",
            "score": 0.00268
        },
        {
            "name": "Atriplex prostrata Boucher ex DC.",
            "id": "1356488",
            "score": 0.00267
        },
        {
            "name": "Rumex thyrsoides Desf.",
            "id": "1360137",
            "score": 0.00264
        },
        {
            "name": "Lythrum portula (L.) D.A.Webb",
            "id": "1393710",
            "score": 0.00263
        },
        {
            "name": "Chenopodium vulvaria L.",
            "id": "1356331",
            "score": 0.00261
        },
        {
            "name": "Rumex alpinus L.",
            "id": "1395643",
            "score": 0.00257
        },
        {
            "name": "Muehlenbeckia complexa (A.Cunn.) Meisn.",
            "id": "1393862",
            "score": 0.0024
        },
        {
            "name": "Boerhavia diffusa L.",
            "id": "1361985",
            "score": 0.00227
        },
        {
            "name": "Malus sylvestris (L.) Mill.",
            "id": "1420379",
            "score": 0.00224
        },
        {
            "name": "Anredera cordifolia (Ten.) Steenis",
            "id": "1363138",
            "score": 0.00224
        },
        {
            "name": "Pyrola chlorantha Sw.",
            "id": "1394997",
            "score": 0.00216
        },
        {
            "name": "Amaranthus hybridus L.",
            "id": "1356475",
            "score": 0.00213
        },
        {
            "name": "Stellaria apetala Ucria",
            "id": "1722525",
            "score": 0.00194
        },
        {
            "name": "Oenothera rosea L'Hér. ex Aiton",
            "id": "1361957",
            "score": 0.00181
        },
        {
            "name": "Claytonia perfoliata Donn ex Willd.",
            "id": "1397353",
            "score": 0.00181
        },
        {
            "name": "Parnassia palustris L.",
            "id": "1359835",
            "score": 0.00175
        },
        {
            "name": "Fallopia baldschuanica (Regel) Holub",
            "id": "1392248",
            "score": 0.00173
        },
        {
            "name": "Claytonia sibirica L.",
            "id": "1391294",
            "score": 0.00171
        },
        {
            "name": "Rumex induratus Boiss. & Reut.",
            "id": "1389815",
            "score": 0.00169
        },
        {
            "name": "Lysimachia nummularia L.",
            "id": "1393708",
            "score": 0.00168
        },
        {
            "name": "Rumex arifolius All.",
            "id": "1395646",
            "score": 0.00152
        },
        {
            "name": "Valeriana locusta L.",
            "id": "1722516",
            "score": 0.00145
        },
        {
            "name": "Rumex scutatus L.",
            "id": "1362485",
            "score": 0.00143
        },
        {
            "name": "Tetragonia tetragonoides (Pall.) Kuntze",
            "id": "1362576",
            "score": 0.0013
        },
        {
            "name": "Stellaria graminea L.",
            "id": "1396446",
            "score": 0.00129
        },
        {
            "name": "Mentha aquatica L.",
            "id": "1356105",
            "score": 0.00128
        },
        {
            "name": "Reynoutria japonica Houtt.",
            "id": "1395150",
            "score": 0.00122
        },
        {
            "name": "Lycium barbarum L.",
            "id": "1360557",
            "score": 0.00121
        },
        {
            "name": "Epilobium angustifolium L.",
            "id": "1359681",
            "score": 0.00117
        },
        {
            "name": "Spergula arvensis L.",
            "id": "1356538",
            "score": 0.0011
        },
        {
            "name": "Parietaria lusitanica L.",
            "id": "1360826",
            "score": 0.00108
        },
        {
            "name": "Cochlearia officinalis L.",
            "id": "1391312",
            "score": 0.00107
        },
        {
            "name": "Lonicera periclymenum L.",
            "id": "1356790",
            "score": 0.00104
        }
    ]
}