{
    "status": "BEST_REF",
    "results": [
        {
            "name": "Kolkwitzia amabilis Graebn.",
            "id": "1390685",
            "score": 0.8279
        },
        {
            "name": "Deutzia scabra Thunb.",
            "id": "1391675",
            "score": 0.02116
        },
        {
            "name": "Philadelphus coronarius L.",
            "id": "1394509",
            "score": 0.01764
        },
        {
            "name": "Weigela florida (Bunge) A.DC.",
            "id": "1390686",
            "score": 0.01022
        },
        {
            "name": "Abelia × grandiflora (Rovelli ex André) Rehder",
            "id": "1423427",
            "score": 0.00351
        },
        {
            "name": "Deutzia gracilis Siebold & Zucc.",
            "id": "1391671",
            "score": 0.00308
        },
        {
            "name": "Dipelta floribunda Maxim.",
            "id": "1491321",
            "score": 0.0024
        }
    ]
}