{
    "status": "BEST_REF",
    "results": [
        {
            "name": "Arctium nemorosum Lej.",
            "id": "1396028",
            "score": 0.3205
        },
        {
            "name": "Arctium lappa L.",
            "id": "1396002",
            "score": 0.30342
        },
        {
            "name": "Arctium minus (Hill) Bernh.",
            "id": "1357244",
            "score": 0.08692
        },
        {
            "name": "Rheum rhaponticum L.",
            "id": "1395161",
            "score": 0.03801
        },
        {
            "name": "Arctium tomentosum Mill.",
            "id": "1396054",
            "score": 0.01273
        },
        {
            "name": "Rheum × hybridum Murray",
            "id": "1432206",
            "score": 0.00919
        },
        {
            "name": "Rumex alpinus L.",
            "id": "1395643",
            "score": 0.00631
        },
        {
            "name": "Tussilago farfara L.",
            "id": "1357950",
            "score": 0.00381
        },
        {
            "name": "Digitalis purpurea L.",
            "id": "1364079",
            "score": 0.0036
        },
        {
            "name": "Silphium perfoliatum L.",
            "id": "1396301",
            "score": 0.00261
        },
        {
            "name": "Cynara cardunculus L.",
            "id": "1355882",
            "score": 0.00241
        },
        {
            "name": "Gunnera tinctoria (Molina) Mirb.",
            "id": "1392660",
            "score": 0.00216
        },
        {
            "name": "Rheum palmatum L.",
            "id": "1398842",
            "score": 0.00212
        },
        {
            "name": "Helianthus giganteus L.",
            "id": "1389511",
            "score": 0.00201
        },
        {
            "name": "Beta macrocarpa Guss.",
            "id": "1356497",
            "score": 0.00191
        },
        {
            "name": "Petasites hybridus (L.) G.Gaertn., B.Mey. & Scherb.",
            "id": "1711822",
            "score": 0.0018
        },
        {
            "name": "Digitalis thapsi L.",
            "id": "1400052",
            "score": 0.00132
        },
        {
            "name": "Rheum officinale Baill.",
            "id": "1420152",
            "score": 0.00122
        },
        {
            "name": "Ligularia dentata (A.Gray) H.Hara",
            "id": "1739014",
            "score": 0.00103
        },
        {
            "name": "Inula helenium L.",
            "id": "1397412",
            "score": 0.00089
        },
        {
            "name": "Heracleum sphondylium L.",
            "id": "1360744",
            "score": 0.00066
        },
        {
            "name": "Angelica sylvestris L.",
            "id": "1394591",
            "score": 0.00061
        },
        {
            "name": "Epilobium parviflorum Schreb.",
            "id": "1359686",
            "score": 0.00061
        },
        {
            "name": "Physalis peruviana L.",
            "id": "1356153",
            "score": 0.00055
        },
        {
            "name": "Tephroseris helenitis (L.) B.Nord.",
            "id": "1396716",
            "score": 0.00044
        },
        {
            "name": "Cucurbita pepo L.",
            "id": "1384485",
            "score": 0.00038
        },
        {
            "name": "Salvia sclarea L.",
            "id": "1358876",
            "score": 0.00035
        },
        {
            "name": "Heracleum mantegazzianum Sommier & Levier",
            "id": "1392753",
            "score": 0.00034
        },
        {
            "name": "Tithonia rotundifolia (Mill.) S.F.Blake",
            "id": "1417905",
            "score": 0.00034
        },
        {
            "name": "Pastinaca sativa L.",
            "id": "1363226",
            "score": 0.00033
        },
        {
            "name": "Adenostyles leucophylla Rchb.",
            "id": "1742051",
            "score": 0.0003
        },
        {
            "name": "Hosta plantaginea (Lam.) Asch.",
            "id": "1412285",
            "score": 0.00029
        },
        {
            "name": "Allium nigrum L.",
            "id": "1360926",
            "score": 0.00028
        },
        {
            "name": "Holcus lanatus L.",
            "id": "1363460",
            "score": 0.00028
        }
    ]
}