{
    "status": "BEST_REF",
    "results": [
        {
            "name": "Cercis canadensis L.",
            "id": "1397806",
            "score": 0.56471
        },
        {
            "name": "Cercis siliquastrum L.",
            "id": "1359162",
            "score": 0.10365
        },
        {
            "name": "Coccoloba acapulcensis Standl.",
            "id": "1657938",
            "score": 0.01697
        },
        {
            "name": "Dichondra carolinensis Michx.",
            "id": "1442527",
            "score": 0.01317
        },
        {
            "name": "Ipomoea purpurea (L.) Roth",
            "id": "1364031",
            "score": 0.01122
        },
        {
            "name": "Reynoutria japonica Houtt.",
            "id": "1395150",
            "score": 0.00984
        },
        {
            "name": "Cercis chinensis Bunge",
            "id": "1418915",
            "score": 0.00595
        },
        {
            "name": "Euphorbia amygdaloides L.",
            "id": "1358525",
            "score": 0.00449
        },
        {
            "name": "Bauhinia galpinii N.E.Br.",
            "id": "1409103",
            "score": 0.00378
        },
        {
            "name": "Ipomoea obscura (L.) Ker Gawl.",
            "id": "1358017",
            "score": 0.00366
        },
        {
            "name": "Gossypium herbaceum L.",
            "id": "1359627",
            "score": 0.00336
        },
        {
            "name": "Dioscorea communis (L.) Caddick & Wilkin",
            "id": "1361109",
            "score": 0.00329
        },
        {
            "name": "Cissampelos pareira L.",
            "id": "1402343",
            "score": 0.00316
        },
        {
            "name": "Adenia cissampeloides (Planch. ex Hook.) Harms",
            "id": "1376542",
            "score": 0.00302
        },
        {
            "name": "Thespesia populnea (L.) Sol. ex Corrêa",
            "id": "1408768",
            "score": 0.00271
        },
        {
            "name": "Calystegia sepium (L.) R.Br.",
            "id": "1426068",
            "score": 0.00239
        },
        {
            "name": "Menispermum canadense L.",
            "id": "1412688",
            "score": 0.00206
        },
        {
            "name": "Hibiscus tiliaceus L.",
            "id": "1408172",
            "score": 0.00202
        },
        {
            "name": "Hedera azorica Carrière",
            "id": "1467317",
            "score": 0.00198
        },
        {
            "name": "Ipomoea muricata (L.) Jacq.",
            "id": "1418481",
            "score": 0.00181
        },
        {
            "name": "Ipomoea nil (L.) Roth",
            "id": "1369244",
            "score": 0.00181
        },
        {
            "name": "Passiflora lutea L.",
            "id": "1419859",
            "score": 0.00179
        },
        {
            "name": "Disanthus cercidifolius Maxim.",
            "id": "1419164",
            "score": 0.00178
        },
        {
            "name": "Jatropha curcas L.",
            "id": "1375622",
            "score": 0.00174
        },
        {
            "name": "Alangium chinense (Lour.) Harms",
            "id": "1388674",
            "score": 0.00166
        },
        {
            "name": "Aristolochia macrophylla Lam.",
            "id": "1396303",
            "score": 0.00149
        },
        {
            "name": "Glumicalyx goseloides (Diels) Hilliard & B.L.Burtt",
            "id": "1688902",
            "score": 0.00133
        },
        {
            "name": "Epimedium alpinum L.",
            "id": "1391952",
            "score": 0.00131
        },
        {
            "name": "Jatropha stevensii G.L.Webster",
            "id": "1546542",
            "score": 0.00129
        },
        {
            "name": "Schnella guianensis (Aubl.) Wunderlin",
            "id": "1714297",
            "score": 0.00129
        },
        {
            "name": "Ipomoea alba L.",
            "id": "1369079",
            "score": 0.00128
        },
        {
            "name": "Dioscorea polygonoides Humb. & Bonpl. ex Willd.",
            "id": "1401595",
            "score": 0.00116
        },
        {
            "name": "Tinospora neocaledonica Forman",
            "id": "1414923",
            "score": 0.00105
        },
        {
            "name": "Cercidiphyllum japonicum Siebold & Zucc. ex J.J.Hoffm. & J.H.Schult.bis",
            "id": "1494963",
            "score": 0.00105
        },
        {
            "name": "Epimedium pinnatum Fisch. ex DC.",
            "id": "1356606",
            "score": 0.00104
        },
        {
            "name": "Aristolochia clematitis L.",
            "id": "1396305",
            "score": 0.00103
        }
    ]
}