{
    "status": "BEST_REF",
    "results": [
        {
            "name": "Euphorbia characias L.",
            "id": "1358543",
            "score": 0.60977
        },
        {
            "name": "Euphorbia × martini Rouy",
            "id": "1545589",
            "score": 0.17952
        },
        {
            "name": "Euphorbia amygdaloides L.",
            "id": "1358525",
            "score": 0.0307
        },
        {
            "name": "Euphorbia dendroides L.",
            "id": "1358548",
            "score": 0.00533
        },
        {
            "name": "Euphorbia esula L.",
            "id": "1392158",
            "score": 0.00201
        },
        {
            "name": "Euphorbia cyparissias L.",
            "id": "1392155",
            "score": 0.00184
        },
        {
            "name": "Euphorbia segetalis L.",
            "id": "1358590",
            "score": 0.00169
        },
        {
            "name": "Euphorbia lucida Waldst. & Kit.",
            "id": "1399176",
            "score": 0.00132
        },
        {
            "name": "Euphorbia mellifera Aiton",
            "id": "1358570",
            "score": 0.0011
        }
    ]
}