{
    "status": "BEST_REF",
    "results": [
        {
            "name": "Phyteuma nigrum F.W.Schmidt",
            "id": "1394547",
            "score": 0.86748
        },
        {
            "name": "Phyteuma ovatum Honck.",
            "id": "1394551",
            "score": 0.1
        },
        {
            "name": "Phyteuma betonicifolium Vill.",
            "id": "1394536",
            "score": 0.05545
        },
        {
            "name": "Phyteuma spicatum L.",
            "id": "1394555",
            "score": 0.02164
        },
        {
            "name": "Phyteuma orbiculare L.",
            "id": "1394548",
            "score": 0.01241
        },
        {
            "name": "Phyteuma persicifolium Hoppe",
            "id": "1490243",
            "score": 0.00192
        },
        {
            "name": "Phyteuma scorzonerifolium Vill.",
            "id": "1394553",
            "score": 0.00103
        }
    ]
}